dustcluster/EC2.py
dustcluster/__init__.py
dustcluster/cluster.py
dustcluster/config.py
dustcluster/console.py
dustcluster/lineterm.py
dustcluster/util.py
dustcluster/commands/__init__.py
dustcluster/commands/atssh.py
dustcluster/commands/builtin.py
dustcluster/commands/clusterops.py
dustcluster/commands/configservice.py
dustcluster/commands/cwlogs.py
dustcluster/commands/filters.py
dustcluster/commands/getput.py
dustcluster/commands/help.py
dustcluster/commands/loglevel.py
dustcluster/commands/tag.py
dustcluster/commands/use.py
dustcluster-0.3.5.data/scripts/dust
dustcluster-0.3.5.dist-info/METADATA
dustcluster-0.3.5.dist-info/WHEEL
dustcluster-0.3.5.dist-info/top_level.txt
dustcluster-0.3.5.dist-info/RECORD
