Metadata-Version: 2.1
Name: dustcluster
Version: 0.3.5
Summary: ssh cluster shell for AWS EC2
Home-page: https://github.com/carlsborg/dust
Author: R Dugal
Author-email: dugal@gmx.com
License: GPL Affero
Platform: UNKNOWN
Classifier: Development Status :: 4 - Beta
Classifier: Environment :: Console
Classifier: Intended Audience :: Developers
Classifier: Intended Audience :: System Administrators
Classifier: Intended Audience :: Information Technology
Classifier: Natural Language :: English
Classifier: License :: OSI Approved :: GNU Affero General Public License v3
Classifier: Operating System :: POSIX
Classifier: Programming Language :: Python
Classifier: Programming Language :: Python :: 3 :: Only
Classifier: Topic :: System :: Installation/Setup
Classifier: Topic :: System :: Systems Administration
Classifier: Topic :: Utilities
Requires-Python: >=3.0.0
Requires-Dist: paramiko (>=2.7.1)
Requires-Dist: pyyaml (>=5.1)
Requires-Dist: boto3 (>=1.12.0)
Requires-Dist: boto (>=2.49.0)
Requires-Dist: troposphere (>=1.5.0)
Requires-Dist: colorama (>=0.3.5)
